<?xml version="1.0" encoding="UTF-8"?>
<LanguageData>
  <AdministeredDrug.label>약물 투여 목격</AdministeredDrug.label>
  
  <AdministeredHardDrug.label>강한 약물 투여 목격</AdministeredHardDrug.label>
  
  <AdministeredRecreationalDrug.label>사교 약물 투여 목격</AdministeredRecreationalDrug.label>
  
  <AteHumanMeat.label>인육을 먹음</AteHumanMeat.label>
  
  <BuildSpecificDef.label>건물 건설</BuildSpecificDef.label>
  
  <CharityRefused_ThreatReward_Joiner.label>피난민 합류 거부함</CharityRefused_ThreatReward_Joiner.label>
  
  <CutTree.label>벌목 현장 목격</CutTree.label>
  
  <DestroyedMineable.label>파괴된 자연벽</DestroyedMineable.label>
  
  <IngestedDrug.label>약물 사용</IngestedDrug.label>
  
  <IngestedHardDrug.label>강한 약물 사용</IngestedHardDrug.label>
  
  <IngestedRecreationalDrug.label>사교 약물 사용 목격</IngestedRecreationalDrug.label>
  
  <InstalledProsthetic.label>보철물 목격</InstalledProsthetic.label>
  
  <Mined.label>채굴 현장 목격</Mined.label>
  
  <MinifiedTreeDied.label>나무가 죽음</MinifiedTreeDied.label>
  
  <Researching.label>연구</Researching.label>
  
  <SowedHumanFoodPlant.label>작물 파종</SowedHumanFoodPlant.label>
  
  <SowedPlant.label>식물 파종</SowedPlant.label>
</LanguageData>
