<?xml version="1.0" encoding="UTF-8"?>
<LanguageData>
  <GlucosoidRush.label>crwdns423316:0crwdne423316:0</GlucosoidRush.label>
  <GlucosoidRush.description>crwdns423318:0crwdne423318:0</GlucosoidRush.description>
  <GlucosoidRush.extraTooltip>crwdns423320:0crwdne423320:0</GlucosoidRush.extraTooltip>
  
  <HemogenAmplified.label>crwdns423322:0crwdne423322:0</HemogenAmplified.label>
  <HemogenAmplified.description>crwdns423324:0crwdne423324:0</HemogenAmplified.description>
  <HemogenAmplified.extraTooltip>crwdns423326:0crwdne423326:0</HemogenAmplified.extraTooltip>
  
  <PsychofluidRush.label>crwdns423328:0crwdne423328:0</PsychofluidRush.label>
  <PsychofluidRush.description>crwdns423330:0crwdne423330:0</PsychofluidRush.description>
  <PsychofluidRush.extraTooltip>crwdns423332:0crwdne423332:0</PsychofluidRush.extraTooltip>
</LanguageData>
