<?xml version="1.0" encoding="utf-8"?>
<LanguageData>

  <!-- Mechanitor -->
  <LetterLabelMechsFeral>crwdns429616:0crwdne429616:0</LetterLabelMechsFeral>
  <LetterMechsFeral>crwdns429618:0{0}crwdnd429618:0{1}crwdne429618:0</LetterMechsFeral>
  <LetterLabelMechlinkInstalled>crwdns429620:0crwdne429620:0</LetterLabelMechlinkInstalled>
  <LetterMechlinkInstalled>crwdns429622:0{PAWN_labelShort}crwdnd429622:0{PAWN_pronoun}crwdnd429622:0{PAWN_labelShort}crwdnd429622:0{PAWN_possessive}crwdnd429622:0{PAWN_pronoun}crwdnd429622:0{PAWN_pronoun}crwdnd429622:0{PAWN_labelShort}crwdne429622:0</LetterMechlinkInstalled>

  <MentalStateReason_Gene>crwdns429624:0crwdne429624:0</MentalStateReason_Gene>

  <LetterLabelBossgroupSummoned>crwdns429626:0{0}crwdne429626:0</LetterLabelBossgroupSummoned>
  <LetterBossgroupSummoned>crwdns429628:0{0}crwdne429628:0</LetterBossgroupSummoned>

  <LetterLabelBossgroupArrived>crwdns429630:0{0}crwdne429630:0</LetterLabelBossgroupArrived>
  <LetterBossgroupArrived>crwdns429632:0{0}crwdnd429632:0{1}crwdnd429632:0{3}crwdnd429632:0{4}crwdne429632:0</LetterBossgroupArrived>

  <LetterLabelCommsConsoleSpawned>crwdns429634:0{LEADER_label}crwdne429634:0</LetterLabelCommsConsoleSpawned>
  <LetterCommsConsoleSpawned>crwdns429636:0{PARENT_label}crwdnd429636:0{LEADER_label}crwdnd429636:0{LEADER_label}crwdnd429636:0{LEADER_label}crwdnd429636:0{REWARDSLIST}crwdne429636:0</LetterCommsConsoleSpawned>

  <LetterLabelBossgroupCallerUnlocked>crwdns429638:0{LEADER_label}crwdne429638:0</LetterLabelBossgroupCallerUnlocked>
  <LetterBossgroupCallerUnlocked>crwdns429640:0{PARENT_label}crwdnd429640:0{LEADER_label}crwdnd429640:0{LEADER_label}crwdnd429640:0{REWARDSLIST}crwdne429640:0</LetterBossgroupCallerUnlocked>

  <LetterLabelMechanitorCasketOpened>crwdns429642:0{0_nameDef}crwdne429642:0</LetterLabelMechanitorCasketOpened>
  <LetterMechanitorCasketOpened>crwdns429644:0{0_possessive}crwdne429644:0</LetterMechanitorCasketOpened>
  <LetterLabelMechanitorCasketFound>crwdns429646:0crwdne429646:0</LetterLabelMechanitorCasketFound>
  <LetterMechanitorCasketFound>crwdns429648:0crwdne429648:0</LetterMechanitorCasketFound>
  
  <!-- Pawns lost because map closed (including mechs) -->
  <LetterPawnsLostIncMechsBecauseMapClosed_Caravan>crwdns429650:0crwdne429650:0</LetterPawnsLostIncMechsBecauseMapClosed_Caravan>
  <LetterPawnsLostIncMechsBecauseMapClosed_Home>crwdns429652:0crwdne429652:0</LetterPawnsLostIncMechsBecauseMapClosed_Home>
  

  <!-- Children -->
  <LetterLabelBecameChild>crwdns429654:0{0_nameDef}crwdne429654:0</LetterLabelBecameChild>
  <LetterLabelBecameAdult>crwdns429656:0{0_nameDef}crwdne429656:0</LetterLabelBecameAdult>
  <LetterBecameChild>crwdns429658:0{0_nameDef}crwdnd429658:0{0_pronoun}crwdne429658:0</LetterBecameChild>
  <LetterBecameChildChanges>crwdns429660:0crwdne429660:0</LetterBecameChildChanges>
  <LetterChildLegalStatus>crwdns429662:0{0_nameDef}crwdnd429662:0{0_parentage}crwdnd429662:0{0_legalStatus}crwdnd429662:0{0_nameDef}crwdnd429662:0{0_legalStatus}crwdne429662:0</LetterChildLegalStatus>
  <LetterChildFollowIdeo>crwdns429664:0{0_labelShort}crwdnd429664:0{1_name}crwdne429664:0</LetterChildFollowIdeo>
  <CannotChangeChildStatusReason>crwdns429666:0{0_nameDef}crwdnd429666:0{0_possessive}crwdne429666:0</CannotChangeChildStatusReason>
  <Enslave>crwdns429668:0crwdne429668:0</Enslave>
  <Emancipate>crwdns429670:0crwdne429670:0</Emancipate>
  <RemainX>crwdns429672:0{0}crwdne429672:0</RemainX>
  <LetterLabelAdopted>crwdns429674:0{BABY_nameDef}crwdne429674:0</LetterLabelAdopted>
  <LetterTextAdopted>crwdns429676:0{BABY_nameDef}crwdnd429676:0{BABY_objective}crwdne429676:0</LetterTextAdopted>

  <LetterLabelThirdTrimester>crwdns429678:0{0_nameDef}crwdne429678:0</LetterLabelThirdTrimester>
  <LetterTextThirdTrimester>crwdns429680:0{0_nameDef}crwdnd429680:0{0_nameDef}crwdne429680:0</LetterTextThirdTrimester>

  <LetterVatBirth>crwdns429682:0{0}crwdne429682:0</LetterVatBirth>
  <LetterVatHealthyBaby>crwdns429684:0{0_nameDef}crwdnd429684:0{1_nameDef}crwdne429684:0</LetterVatHealthyBaby>
  <LetterVatHealthyBabyNoParents>crwdns429686:0crwdne429686:0</LetterVatHealthyBabyNoParents>
  <LetterVatInfantIllness>crwdns429688:0{0_nameDef}crwdnd429688:0{1_nameDef}crwdne429688:0</LetterVatInfantIllness>
  <LetterVatInfantIllnessNoParents>crwdns429690:0crwdne429690:0</LetterVatInfantIllnessNoParents>
  <LetterVatStillborn>crwdns429692:0{0_nameDef}crwdnd429692:0{1_nameDef}crwdne429692:0</LetterVatStillborn>
  <LetterVatSillbornNoParents>crwdns429694:0crwdne429694:0</LetterVatSillbornNoParents>
  <LetterColonistPregnancyLaborLabel>crwdns429696:0{0_labelShort}crwdne429696:0</LetterColonistPregnancyLaborLabel>
  <LetterColonistPregnancyLabor>crwdns429698:0{0_labelShort}crwdnd429698:0{0_labelShort}crwdne429698:0</LetterColonistPregnancyLabor>
  <LetterPartColonistDiedAfterChildbirth>crwdns429700:0{0_labelShort}crwdne429700:0</LetterPartColonistDiedAfterChildbirth>
  <LetterPartSurrogacy>crwdns429702:0{0_labelShort}crwdnd429702:0{1_labelShort}crwdne429702:0</LetterPartSurrogacy>
  <InbredBabyBorn>crwdns429704:0crwdne429704:0</InbredBabyBorn>

  <BabyAlreadyNamed>crwdns429706:0{0_nameDef}crwdne429706:0</BabyAlreadyNamed>
  <NameBaby>crwdns429708:0crwdne429708:0</NameBaby>
  <Immediately>crwdns429710:0crwdne429710:0</Immediately>
  <Within>crwdns429712:0crwdne429712:0</Within>
  <LetterPartTempBabyName>crwdns429714:0{0_nameFull}crwdne429714:0</LetterPartTempBabyName>
  <LetterPartLiveBirthNameDeadline>crwdns429716:0{0}crwdne429716:0</LetterPartLiveBirthNameDeadline>
  <LetterPartStillbirthNameDeadline>crwdns429718:0crwdne429718:0</LetterPartStillbirthNameDeadline>
  <LetterPartNameBabyAdopt>crwdns429720:0{0_nameFull}crwdnd429720:0{1}crwdne429720:0</LetterPartNameBabyAdopt>

  <BirthdayGrowthMoment>crwdns429722:0{PAWNNAME}crwdne429722:0</BirthdayGrowthMoment>
  <BirthdayBiologicalGrowthMoment>crwdns429724:0{0_nameFull}crwdnd429724:0{1}crwdne429724:0</BirthdayBiologicalGrowthMoment>
  <BirthdayBiologicalAgeWorkTypes>crwdns429726:0{0_nameDef}crwdne429726:0</BirthdayBiologicalAgeWorkTypes>
  <BirthdayPickPassion>crwdns429728:0{0_nameDef}crwdnd429728:0{0_possessive}crwdne429728:0</BirthdayPickPassion>
  <BirthdayPickPassions>crwdns429730:0{1}crwdnd429730:0{0_nameDef}crwdnd429730:0{0_possessive}crwdne429730:0</BirthdayPickPassions>
  <BirthdayPickTrait>crwdns429732:0{0_nameDef}crwdne429732:0</BirthdayPickTrait>
  <BirthdayGrowthTier>crwdns429734:0{0_nameDef}crwdnd429734:0{1}crwdne429734:0</BirthdayGrowthTier>
  <BirthdayChooseHowPawnWillGrow>crwdns429736:0{0_nameDef}crwdne429736:0</BirthdayChooseHowPawnWillGrow>

  <BirthdayPassionArchive>crwdns429738:0{0}crwdne429738:0</BirthdayPassionArchive>
  <BirthdayTraitArchive>crwdns429740:0{0}crwdne429740:0</BirthdayTraitArchive>
  <BirthdayNoTraitChoice>crwdns429742:0crwdne429742:0</BirthdayNoTraitChoice>
  <BirthdayNoTraitChoiceTooltip>crwdns429744:0{0}crwdne429744:0</BirthdayNoTraitChoiceTooltip>

  <BirthdayMakeChoices>crwdns429746:0crwdne429746:0</BirthdayMakeChoices>
  <BirthdayNickname>crwdns429748:0{0}crwdnd429748:0{1}crwdne429748:0</BirthdayNickname>
  <SelectATrait>crwdns429750:0crwdne429750:0</SelectATrait>
  <SelectPassionSingular>crwdns429752:0crwdne429752:0</SelectPassionSingular>
  <SelectPassionsPlural>crwdns429754:0{0}crwdne429754:0</SelectPassionsPlural>
  <Later>crwdns429756:0crwdne429756:0</Later>
  
  <LetterLabelMechlinkAvailable>crwdns429758:0crwdne429758:0</LetterLabelMechlinkAvailable>
  <LetterMechlinkAvailable>crwdns429760:0{0}crwdne429760:0</LetterMechlinkAvailable>

  <!-- Genes -->
  <LetterLabelXenogermOrderedImplanted>crwdns429762:0crwdne429762:0</LetterLabelXenogermOrderedImplanted>
  <LetterXenogermOrderedImplanted>crwdns429764:0{PAWN_nameDef}crwdnd429764:0{MEDICINENEEDED}crwdnd429764:0{BEDINFO}crwdnd429764:0{MEDICINEINFO}crwdnd429764:0{PAWN_nameDef}crwdne429764:0</LetterXenogermOrderedImplanted>
  <XenogermOrderedImplantedBedNeeded>crwdns429766:0{PAWN_nameDef}crwdne429766:0</XenogermOrderedImplantedBedNeeded>
  <XenogermOrderedImplantedMedicineNeeded>crwdns429768:0{MEDICINENEEDED}crwdne429768:0</XenogermOrderedImplantedMedicineNeeded>
  <LetterLabelInvoluntaryDeathrest>crwdns429770:0crwdne429770:0</LetterLabelInvoluntaryDeathrest>
  <LetterLabelRegenerationComa>crwdns429772:0crwdne429772:0</LetterLabelRegenerationComa>
  <LetterTextInvoluntaryDeathrestOrComa>crwdns429774:0{PAWN_nameDef}crwdnd429774:0{PAWN_objective}crwdnd429774:0{HEDIFFINFO}crwdne429774:0</LetterTextInvoluntaryDeathrestOrComa>
  <LetterTextDeathrest>crwdns429776:0{PAWN_pronoun}crwdne429776:0</LetterTextDeathrest>
  <LetterTextRegenerationComa>crwdns429778:0{PAWN_pronoun}crwdne429778:0</LetterTextRegenerationComa>
  <DeathrestLostSkill>crwdns429780:0{PAWN_nameDef}crwdnd429780:0{XPLOSS}crwdnd429780:0{PAWN_possessive}crwdnd429780:0{SKILL}crwdne429780:0</DeathrestLostSkill>
  <DeathrestLethalDamage>crwdns429782:0crwdne429782:0</DeathrestLethalDamage>

  <LetterLabelSanguophageWaitingToReimplant>crwdns429784:0crwdne429784:0</LetterLabelSanguophageWaitingToReimplant>
  <LetterTextSanguophageWaitingToReimplant>crwdns429786:0{PAWN_objective}crwdnd429786:0{PAWN_possessive}crwdnd429786:0{PAWN_nameDef}crwdnd429786:0{PAWN_possessive}crwdnd429786:0{PAWN_nameDef}crwdnd429786:0{DURATION}crwdne429786:0</LetterTextSanguophageWaitingToReimplant>

  <LetterLabelGenesImplanted>crwdns429788:0crwdne429788:0</LetterLabelGenesImplanted>
  <LetterTextGenesImplanted>crwdns429790:0{CASTER_nameDef}crwdnd429790:0{CASTER_possessive}crwdnd429790:0{TARGET_nameDef}crwdnd429790:0{TARGET_objective}crwdnd429790:0{TARGET_nameDef}crwdnd429790:0{COMADURATION}crwdnd429790:0{TARGET_possessive}crwdnd429790:0{CASTER_nameDef}crwdnd429790:0{SHOCKDURATION}crwdnd429790:0{CASTER_possessive}crwdnd429790:0{CASTER_nameDef}crwdnd429790:0{CASTER_possessive}crwdnd429790:0{CASTER_possessive}crwdnd429790:0{CASTER_pronoun}crwdne429790:0</LetterTextGenesImplanted>
  
  <RefugeePodCrashBaby>crwdns429792:0{PAWN_nameDef}crwdnd429792:0{PAWN_factionName}crwdnd429792:0{PAWN_objective}crwdnd429792:0{PAWN_objective}crwdne429792:0</RefugeePodCrashBaby>
  <RefugeePodCrashBabyHasParent>crwdns429794:0{PAWN_nameDef}crwdne429794:0</RefugeePodCrashBabyHasParent>

  <LetterPsychicBondCreated>crwdns429796:0{BONDPAWN_nameDef}crwdnd429796:0{OTHERPAWN_nameDef}crwdnd429796:0{OTHERPAWN_nameDef}crwdnd429796:0{BONDPAWN_nameDef}crwdne429796:0</LetterPsychicBondCreated>

  <LetterPsychicBondCreatedLovinLabel>crwdns429798:0crwdne429798:0</LetterPsychicBondCreatedLovinLabel>
  <LetterPsychicBondCreatedLovinText>crwdns429800:0{BONDPAWN_nameDef}crwdnd429800:0{OTHERPAWN_nameDef}crwdnd429800:0{OTHERPAWN_nameDef}crwdnd429800:0{BONDPAWN_nameDef}crwdne429800:0</LetterPsychicBondCreatedLovinText>

</LanguageData>
