<?xml version="1.0" encoding="UTF-8"?>
<LanguageData>
  <ParticipatedInRaid_Required.stages.participated_in_raid.label>crwdns442562:0crwdne442562:0</ParticipatedInRaid_Required.stages.participated_in_raid.label>
  <ParticipatedInRaid_Required.stages.participated_in_raid.description>crwdns442564:0crwdne442564:0</ParticipatedInRaid_Required.stages.participated_in_raid.description>
  
  <ParticipatedInRaid_Respected.stages.participated_in_raid.label>crwdns442566:0crwdne442566:0</ParticipatedInRaid_Respected.stages.participated_in_raid.label>
  <ParticipatedInRaid_Respected.stages.participated_in_raid.description>crwdns442568:0crwdne442568:0</ParticipatedInRaid_Respected.stages.participated_in_raid.description>
  
  <RecentConquest_Required.stages.recent_conquest.label>crwdns442570:0crwdne442570:0</RecentConquest_Required.stages.recent_conquest.label>
  <RecentConquest_Required.stages.recent_conquest.description>crwdns442572:0crwdne442572:0</RecentConquest_Required.stages.recent_conquest.description>
  <RecentConquest_Required.stages.no_recent_conquest.label>crwdns442574:0crwdne442574:0</RecentConquest_Required.stages.no_recent_conquest.label>
  <RecentConquest_Required.stages.no_recent_conquest.description>crwdns442576:0crwdne442576:0</RecentConquest_Required.stages.no_recent_conquest.description>
  
  <RecentConquest_Respected.stages.recent_conquest.label>crwdns442578:0crwdne442578:0</RecentConquest_Respected.stages.recent_conquest.label>
  <RecentConquest_Respected.stages.recent_conquest.description>crwdns442580:0crwdne442580:0</RecentConquest_Respected.stages.recent_conquest.description>
  <RecentConquest_Respected.stages.no_recent_conquest.label>crwdns442582:0crwdne442582:0</RecentConquest_Respected.stages.no_recent_conquest.label>
  <RecentConquest_Respected.stages.no_recent_conquest.description>crwdns442584:0crwdne442584:0</RecentConquest_Respected.stages.no_recent_conquest.description>
</LanguageData>
